das/__init__.py
das/common.py
das/db.py
das/divideandscan.py
das/dns.py
das/drawnmap.py
das/parsenmap.py
das/parsers/__init__.py
das/parsers/generic.py
das/parsers/masscan.py
das/parsers/masscan_import.py
das/parsers/naabu.py
das/parsers/nimscan.py
das/parsers/nmap.py
das/parsers/rustscan.py
das/parsers/sx.py
das/report.py
das/scan.py
divideandscan-1.0.3.dist-info/LICENSE
divideandscan-1.0.3.dist-info/METADATA
divideandscan-1.0.3.dist-info/WHEEL
divideandscan-1.0.3.dist-info/entry_points.txt
divideandscan-1.0.3.dist-info/RECORD
