Metadata-Version: 2.1
Name: divideandscan
Version: 1.0.3
Summary: Divide full port scan results and use it for targeted Nmap runs
Home-page: https://github.com/snovvcrash/DivideAndScan
License: BSD-2-Clause
Keywords: pentest,scan,nmap,masscan,rustscan
Author: Sam Freeside
Author-email: snovvcrash@protonmail.ch
Requires-Python: >=3.9,<3.12
Classifier: Environment :: Console
Classifier: License :: OSI Approved :: BSD License
Classifier: Programming Language :: Python :: 3
Classifier: Programming Language :: Python :: 3.9
Classifier: Programming Language :: Python :: 3.10
Classifier: Programming Language :: Python :: 3.11
Classifier: Topic :: Security
Requires-Dist: dash (>=2.5.1,<3.0.0)
Requires-Dist: defusedxml (>=0.7.1,<0.8.0)
Requires-Dist: dnspython (>=2.3.0,<3.0.0)
Requires-Dist: netaddr (>=0.8.0,<0.9.0)
Requires-Dist: networkx (>=2.8.4,<3.0.0)
Requires-Dist: pandas (>=2.0.0,<3.0.0)
Requires-Dist: plotly (>=5.8.2,<6.0.0)
Requires-Dist: python-nmap (>=0.7.1,<0.8.0)
Requires-Dist: scipy (>=1.8.1,<2.0.0)
Requires-Dist: tinydb (>=4.6.1,<5.0.0)
Project-URL: Repository, https://github.com/snovvcrash/DivideAndScan
